setup.py
timelines/__init__.py
timelines.egg-info/PKG-INFO
timelines.egg-info/SOURCES.txt
timelines.egg-info/dependency_links.txt
timelines.egg-info/entry_points.txt
timelines.egg-info/not-zip-safe
timelines.egg-info/top_level.txt