Metadata-Version: 1.0
Name: timelines
Version: 0.1
Summary: timespan and scheduling helpers for Python
Home-page: UNKNOWN
Author: Ethan Jucovy
Author-email: ethan@boldprogressives.org
License: BSD
Platform: UNKNOWN
Classifier: Development Status :: 4 - Beta
Classifier: License :: OSI Approved :: BSD License
